{
  "name": "João Silva",
  "avatar": "https://exemplo.com/avatar.jpg",
  "description": "Desenvolvedor de software apaixonado por tecnologia e inovação.",
  "links": [
    {
      "title": "Meu Portfólio",
      "url": "https://meuportfolio.com"
    },
    {
      "title": "Meu Blog",
      "url": "https://meublog.com"
    }
  ],
  "socialLinks": {
    "LinkedIn": "https://linkedin.com/in/joaosilva",
    "Facebook": "https://facebook.com/joaosilva",
    "Instagram": "https://instagram.com/joaosilva"
  }
}
